aiprep/__init__.py
aiprep/__main__.py
aiprep/cli.py
aiprep/core.py
aiprep-1.0.3.dist-info/licenses/LICENSE
aiprep-1.0.3.dist-info/METADATA
aiprep-1.0.3.dist-info/WHEEL
aiprep-1.0.3.dist-info/entry_points.txt
aiprep-1.0.3.dist-info/top_level.txt
aiprep-1.0.3.dist-info/RECORD
