Metadata-Version: 2.4
Name: aiprep
Version: 1.0.3
Summary: Prepare multiple source code files for AI prompts, with clipboard support.
Home-page: https://github.com/jeremiah-k/aiprep
Author: jeremiah-k
License: MIT
Classifier: Programming Language :: Python :: 3
Classifier: License :: OSI Approved :: MIT License
Classifier: Operating System :: OS Independent
Requires-Python: >=3.9
License-File: LICENSE
Requires-Dist: pyperclip
Requires-Dist: pathspec
Dynamic: license-file
